SearchScrape/__init__.py
SearchScrape/main.py
SearchScrape-0.1.0.dist-info/LICENSE
SearchScrape-0.1.0.dist-info/METADATA
SearchScrape-0.1.0.dist-info/WHEEL
SearchScrape-0.1.0.dist-info/top_level.txt
SearchScrape-0.1.0.dist-info/RECORD
