Metadata-Version: 2.1
Name: SearchScrape
Version: 0.1.0
License-File: LICENSE
Requires-Dist: beautifulsoup4
Requires-Dist: requests
